{
  "experiment": "exp_86_seed42_stability",
  "timestamp": "20260531_154442",
  "seeds": [
    42,
    142
  ],
  "per_seed": [
    {
      "seed": 42,
      "steps": 1600,
      "N0": 72,
      "narrative_active_steps": 53,
      "narrative_total_sampled": 240,
      "civilization_steps": 21,
      "level_counts": {
        "MINI": 0,
        "INSTITUTIONAL": 525,
        "CIVILIZATION": 678
      },
      "odi_max": 0.7278,
      "odi_mean": 0.066,
      "msi_max": 0.3307,
      "msi_mean": 0.1924,
      "momentum_cache": {
        "n_categories": 4,
        "max_heat": 25.3674,
        "mean_heat": 15.2757,
        "categories": {
          "internal_layer_0_R1_high": 25.367,
          "internal_layer_0_R3_high": 13.441,
          "internal_layer_0_R0_high": 12.099,
          "internal_layer_0_R2_high": 10.195
        }
      },
      "elapsed_s": 55.5
    },
    {
      "seed": 142,
      "steps": 1600,
      "N0": 72,
      "narrative_active_steps": 27,
      "narrative_total_sampled": 240,
      "civilization_steps": 8,
      "level_counts": {
        "MINI": 0,
        "INSTITUTIONAL": 92,
        "CIVILIZATION": 131
      },
      "odi_max": 0.6968,
      "odi_mean": 0.0657,
      "msi_max": 0.3039,
      "msi_mean": 0.2161,
      "momentum_cache": {
        "n_categories": 4,
        "max_heat": 9.6637,
        "mean_heat": 6.2456,
        "categories": {
          "internal_layer_0_R2_high": 9.664,
          "internal_layer_0_R3_high": 6.415,
          "internal_layer_0_R1_high": 5.447,
          "internal_layer_0_R0_high": 3.457
        }
      },
      "elapsed_s": 59.8
    }
  ],
  "cross_seed": {
    "h1_all_civ_ge_5": true
  }
}